{"Eta": 0.3, "Alpha": 0.75, "Gain": 0.99, "Layers": [{"Func": null, "Neurons": [{"Bias": null, "Conn": []}, {"Bias": null, "Conn": []}]}, {"Func": "TanH", "Neurons": [{"Bias": {"Val": 1.0, "Wght": -0.766127089357026}, "Conn": [{"LSrc": 0, "NSrc": 0, "Wght": 2.324882044845701}, {"LSrc": 0, "NSrc": 1, "Wght": 2.3485774082551347}]}, {"Bias": {"Val": 1.0, "Wght": -1.9424693424118917}, "Conn": [{"LSrc": 0, "NSrc": 0, "Wght": 1.5228889957000789}, {"LSrc": 0, "NSrc": 1, "Wght": 1.5198516191563423}]}]}, {"Func": "TanH", "Neurons": [{"Bias": {"Val": 1.0, "Wght": -0.5069676181206704}, "Conn": [{"LSrc": 1, "NSrc": 0, "Wght": 1.9781982281270396}, {"LSrc": 1, "NSrc": 1, "Wght": -1.8513808709006785}]}]}]}